pyjudo/__init__.py
pyjudo/__init__.pyi
pyjudo/disposable.py
pyjudo/disposable.pyi
pyjudo/exceptions.py
pyjudo/exceptions.pyi
pyjudo/factory.py
pyjudo/factory.pyi
pyjudo/py.typed
pyjudo/resolver.py
pyjudo/resolver.pyi
pyjudo/scope_stack.py
pyjudo/scope_stack.pyi
pyjudo/service_cache.py
pyjudo/service_cache.pyi
pyjudo/service_container.py
pyjudo/service_container.pyi
pyjudo/service_entry_collection.py
pyjudo/service_entry_collection.pyi
pyjudo/service_scope.py
pyjudo/service_scope.pyi
pyjudo/core/__init__.py
pyjudo/core/__init__.pyi
pyjudo/core/iresolver.py
pyjudo/core/iresolver.pyi
pyjudo/core/iservice_cache.py
pyjudo/core/iservice_cache.pyi
pyjudo/core/iservice_container.py
pyjudo/core/iservice_container.pyi
pyjudo/core/iservice_entry_collection.py
pyjudo/core/iservice_entry_collection.pyi
pyjudo/core/iservice_scope.py
pyjudo/core/iservice_scope.pyi
pyjudo/core/iservice_stack.py
pyjudo/core/iservice_stack.pyi
pyjudo/core/service_entry.py
pyjudo/core/service_entry.pyi
pyjudo/core/service_life.py
pyjudo/core/service_life.pyi
pyjudo-0.7.1.dist-info/METADATA
pyjudo-0.7.1.dist-info/WHEEL
pyjudo-0.7.1.dist-info/RECORD
