Metadata-Version: 2.3
Name: pyjudo
Version: 0.7.1
Summary: Simple dependency injection for Python.
Requires-Python: >=3.12
